hypothesis_protobuf/__init__.py
hypothesis_protobuf/_version.py
hypothesis_protobuf/strategies.py
hypothesis_protobuf/tests/__init__.py
hypothesis_protobuf-0.1.0.post1.dist-info/DESCRIPTION.rst
hypothesis_protobuf-0.1.0.post1.dist-info/METADATA
hypothesis_protobuf-0.1.0.post1.dist-info/RECORD
hypothesis_protobuf-0.1.0.post1.dist-info/WHEEL
hypothesis_protobuf-0.1.0.post1.dist-info/metadata.json
hypothesis_protobuf-0.1.0.post1.dist-info/top_level.txt
