Metadata-Version: 2.0
Name: hypothesis-protobuf
Version: 0.1.0.post1
Summary: Hypothesis strategies for Google Protocol Buffers
Home-page: https://github.com/Julian/hypothesis-protobuf
Author: Julian Berman
Author-email: Julian@GrayVines.com
License: MIT
Platform: UNKNOWN
Classifier: Development Status :: 3 - Alpha
Classifier: License :: OSI Approved :: MIT License
Classifier: Operating System :: OS Independent
Classifier: Programming Language :: Python
Classifier: Programming Language :: Python :: 2.7
Classifier: Programming Language :: Python :: 2
Classifier: Programming Language :: Python :: Implementation :: CPython
Classifier: Programming Language :: Python :: Implementation :: PyPy
